socrate/__init__.py
socrate/conf.py
socrate/system.py
socrate-0.2.0.dist-info/LICENSE.md
socrate-0.2.0.dist-info/METADATA
socrate-0.2.0.dist-info/WHEEL
socrate-0.2.0.dist-info/top_level.txt
socrate-0.2.0.dist-info/RECORD
