Metadata-Version: 2.1
Name: socrate
Version: 0.2.0
Summary: Socrate daemon utilities
Home-page: https://github.com/mailu/socrate.git
Author: Pierre Jaury
Author-email: pierre@jaury.eu
License: UNKNOWN
Platform: UNKNOWN
Requires-Dist: jinja2
Requires-Dist: tenacity
